{"conclusion":"success","createdAt":"2026-07-14T21:59:28Z","jobs":[{"completedAt":"2026-07-14T21:59:37Z","conclusion":"success","databaseId":87215523891,"name":"build","startedAt":"2026-07-14T21:59:31Z","status":"completed","steps":[{"completedAt":"2026-07-14T21:59:31Z","conclusion":"success","name":"Set up job","number":1,"startedAt":"2026-07-14T21:59:31Z","status":"completed"},{"completedAt":"2026-07-14T21:59:36Z","conclusion":"success","name":"marker","number":2,"startedAt":"2026-07-14T21:59:31Z","status":"completed"},{"completedAt":"2026-07-14T21:59:36Z","conclusion":"success","name":"Complete job","number":3,"startedAt":"2026-07-14T21:59:36Z","status":"completed"}],"url":"https://github.com/Bnjoroge1/aksh-conformance/actions/runs/29371470819/job/87215523891"}],"status":"completed","updatedAt":"2026-07-14T21:59:38Z","url":"https://github.com/Bnjoroge1/aksh-conformance/actions/runs/29371470819"}